across/__init__.py
across/tools/__init__.py
across/tools/_version.py
across/tools/example_module.py
across/tools/py.typed
across/tools/core/__init__.py
across/tools/core/config.py
across/tools/core/math.py
across/tools/core/enums/__init__.py
across/tools/core/enums/constraint_type.py
across/tools/core/enums/depth_unit.py
across/tools/core/enums/energy_unit.py
across/tools/core/enums/frequency_unit.py
across/tools/core/enums/wavelength_unit.py
across/tools/core/schemas/__init__.py
across/tools/core/schemas/bandpass.py
across/tools/core/schemas/base.py
across/tools/core/schemas/coordinate.py
across/tools/core/schemas/custom_types.py
across/tools/core/schemas/exceptions.py
across/tools/core/schemas/healpix_order.py
across/tools/core/schemas/polygon.py
across/tools/core/schemas/roll_angle.py
across/tools/core/schemas/tle.py
across/tools/core/schemas/visibility.py
across/tools/ephemeris/__init__.py
across/tools/ephemeris/base.py
across/tools/ephemeris/ground_ephem.py
across/tools/ephemeris/jpl_ephem.py
across/tools/ephemeris/spice_ephem.py
across/tools/ephemeris/tle_ephem.py
across/tools/footprint/__init__.py
across/tools/footprint/footprint.py
across/tools/footprint/healpix_joins.py
across/tools/footprint/projection.py
across/tools/tle/__init__.py
across/tools/tle/exceptions.py
across/tools/tle/tle.py
across/tools/visibility/__init__.py
across/tools/visibility/base.py
across/tools/visibility/constraints_constructor.py
across/tools/visibility/ephemeris_visibility.py
across/tools/visibility/joint_visibility.py
across/tools/visibility/constraints/__init__.py
across/tools/visibility/constraints/alt_az.py
across/tools/visibility/constraints/base.py
across/tools/visibility/constraints/earth_limb.py
across/tools/visibility/constraints/moon_angle.py
across/tools/visibility/constraints/polygon.py
across/tools/visibility/constraints/saa.py
across/tools/visibility/constraints/sun_angle.py
across_tools-1.1.0.dist-info/licenses/LICENSE
across_tools-1.1.0.dist-info/METADATA
across_tools-1.1.0.dist-info/WHEEL
across_tools-1.1.0.dist-info/top_level.txt
across_tools-1.1.0.dist-info/RECORD
