Metadata-Version: 2.4
Name: across-tools
Version: 1.1.0
Author-email: "Samuel D. Wyatt" <samuel.d.wyatt@nasa.gov>, "Jamie A. Kennea" <jak51@psu.edu>, Craig Pellegrino <craig.m.pellegrino@nasa.gov>, "Nitzan N. Frock" <nitzan.n.frock@nasa.gov>
Maintainer-email: "Samuel D. Wyatt" <samuel.d.wyatt@nasa.gov>, "Jamie A. Kennea" <jak51@psu.edu>, Craig Pellegrino <craig.m.pellegrino@nasa.gov>, "Nitzan N. Frock" <nitzan.n.frock@nasa.gov>
License:                                  Apache License
Project-URL: Source Code, https://github.com/NASA-ACROSS/across-tools
Classifier: Development Status :: 4 - Beta
Classifier: Intended Audience :: Developers
Classifier: Intended Audience :: Science/Research
Classifier: Operating System :: OS Independent
Classifier: Programming Language :: Python
Requires-Python: >=3.10
License-File: LICENSE
Requires-Dist: astropy>=5
Requires-Dist: numpy>=1.2
Requires-Dist: healpy>=1.1
Requires-Dist: pydantic>=2.1
Requires-Dist: astroquery>=0.4
Requires-Dist: sgp4>=2.2
Requires-Dist: spiceypy>=6.0.0
Requires-Dist: httpx>=0.6
Requires-Dist: spacetrack>=1.0.0
Requires-Dist: pydantic_settings>=2.0
Requires-Dist: shapely>=2.0.4
Provides-Extra: dev
Requires-Dist: jupyter; extra == "dev"
Requires-Dist: mypy; extra == "dev"
Requires-Dist: pre-commit; extra == "dev"
Requires-Dist: pytest; extra == "dev"
Requires-Dist: pytest-cov; extra == "dev"
Requires-Dist: ruff; extra == "dev"
Requires-Dist: sphinx-autoapi; extra == "dev"
Requires-Dist: nbsphinx; extra == "dev"
Requires-Dist: sphinx-copybutton; extra == "dev"
Requires-Dist: sphinx-rtd-theme; extra == "dev"
Requires-Dist: types-shapely; extra == "dev"
Dynamic: license-file
